<?xml version="1.0" encoding="UTF-8"?><RESULT xmlns:mb="http://musicbrainz.org/ns/mmd-2.0#">
<RECORD>
  <ITEM ANGIE-VAR="?albumId">NOT DEFINED</ITEM>
  <ITEM ANGIE-VAR="?duration"/>
  <ITEM ANGIE-VAR="?songId">268ae3c1-f225-474c-a4ba-a9d1bc2381f9</ITEM>
  <ITEM ANGIE-VAR="?songName">Polka Dots and Moonbeams</ITEM>
</RECORD>
<RECORD>
  <ITEM ANGIE-VAR="?albumId">NOT DEFINED</ITEM>
  <ITEM ANGIE-VAR="?duration"/>
  <ITEM ANGIE-VAR="?songId">8b089a2b-40be-44a4-a7cc-7e2336f28ade</ITEM>
  <ITEM ANGIE-VAR="?songName">I'll Be Seeing You</ITEM>
</RECORD></RESULT>