<?xml version="1.0" encoding="UTF-8"?><metadata xmlns="http://musicbrainz.org/ns/mmd-2.0#"><label-list count="1"><label type-id="7aaa37fe-2def-3476-b359-80245850062d" id="75d1c742-d385-4d50-8358-502207d2382e" type="Original Production"><name>Gurdulu</name><sort-name>Gurdulu</sort-name><country>FR</country><area id="08310658-51eb-3801-80de-5a0739207115"><name>France</name><sort-name>France</sort-name><iso-3166-1-code-list><iso-3166-1-code>FR</iso-3166-1-code></iso-3166-1-code-list></area></label></label-list></metadata>
